<?xml version="1.0" encoding="UTF-8"?>
<beans xmlns="http://www.springframework.org/schema/beans"
       xmlns:xsi="http://www.w3.org/2001/XMLSchema-instance"
       xmlns:context="http://www.springframework.org/schema/context" xmlns:tx="http://www.springframework.org/schema/tx"
       xmlns:aop="http://www.springframework.org/schema/aop"
       xsi:schemaLocation="http://www.springframework.org/schema/beans
       http://www.springframework.org/schema/beans/spring-beans.xsd
       http://www.springframework.org/schema/context
        http://www.springframework.org/schema/context/spring-context.xsd
        http://www.springframework.org/schema/tx
         http://www.springframework.org/schema/tx/spring-tx.xsd
         http://www.springframework.org/schema/aop
         http://www.springframework.org/schema/aop/spring-aop.xsd">
    <context:component-scan base-package="statement.annotation"/>
    <!--    配置数据源-->
    <bean id="dataSource" class="org.springframework.jdbc.datasource.DriverManagerDataSource">
        <!--        mysql数据库驱动-->
        <property name="driverClassName" value="com.mysql.jdbc.Driver"/>
        <property name="url" value="jdbc:mysql://47.106.246.216/sampledb?characterEncoding=utf8&amp;useUnicode=true&amp;useSSL=false&amp;serverTimezone=Asia/Shanghai"/>
        <property name="username" value="root"/>
        <property name="password" value="123456"/>
    </bean>
    <!-- 配置Jdbc模板  -->
    <bean id="jdbcTemplate" class="org.springframework.jdbc.core.JdbcTemplate">
        <property name="dataSource" ref="dataSource" />
    </bean>

    <!--    为数据源添加事务管理器-->
    <bean id="txManager" class="org.springframework.jdbc.datasource.DataSourceTransactionManager">
        <property name="dataSource" ref="dataSource"/>
    </bean>

    <!--    编写同时声明事务-->
    <tx:advice id="myAdvice" transaction-manager="txManager">
        <tx:attributes>
            <!--            *表示任意方法-->
            <tx:method name="*"/>
        </tx:attributes>
    </tx:advice>

    <tx:annotation-driven transaction-manager="txManager"/>
</beans>